mysqlmigratorpostgresql/__init__.py
mysqlmigratorpostgresql/connect_mysql.py
mysqlmigratorpostgresql/connect_postgresql.py
mysqlmigratorpostgresql/migrator.py
mysqlmigratorpostgresql-0.1.0.dist-info/LICENCE
mysqlmigratorpostgresql-0.1.0.dist-info/METADATA
mysqlmigratorpostgresql-0.1.0.dist-info/WHEEL
mysqlmigratorpostgresql-0.1.0.dist-info/top_level.txt
mysqlmigratorpostgresql-0.1.0.dist-info/RECORD
