Metadata-Version: 2.1
Name: mysqlmigratorpostgresql
Version: 0.1.0
Summary: A library to migrate MySQL databases to PostgreSQL with ease and automation.
Home-page: https://github.com/archenthusiastic/mysqlmigratorpostgresql
Author: archenthusiastic
Author-email: abuawadsantiago@gmail.com
License: MIT
Project-URL: Documentation, https://github.com/archenthusiastic/mysqlmigratorpostgresql#readme
Project-URL: Source, https://github.com/archenthusiastic/mysqlmigratorpostgresql
Project-URL: Tracker, https://github.com/archenthusiastic/mysqlmigratorpostgresql/issues
Keywords: mysql,postgresql,database migration,python
Classifier: Development Status :: 4 - Beta
Classifier: Programming Language :: Python :: 3
Classifier: License :: OSI Approved :: MIT License
Classifier: Operating System :: OS Independent
Classifier: Topic :: Database
Requires-Python: >=3.7
License-File: LICENCE
Requires-Dist: mysql-connector-python
Requires-Dist: psycopg2
